menu/__init__.py
menu/example.py
menu/menu.py
menu/classes/exceptions.py
menu/classes/menu_options.py
menu/classes/theme.py
menu/functions/check_types.py
menu/functions/clear_buffer.py
menu/functions/cls.py
menu/functions/debugprint.py
menu/functions/menuinput.py
menu/functions/menuprint.py
menu/functions/print_header.py
menu.py-0.3.14.dist-info/LICENSE
menu.py-0.3.14.dist-info/METADATA
menu.py-0.3.14.dist-info/WHEEL
menu.py-0.3.14.dist-info/top_level.txt
menu.py-0.3.14.dist-info/RECORD
