Metadata-Version: 2.1
Name: menu.py
Version: 0.3.14
Summary: A simple python package for in-terminal menu creation on Windows
Home-page: https://github.com/readyyeti/menu.py
Author: deadyeti
Author-email: deadyeti@deadyeti.ca
License: UNKNOWN
Project-URL: Bug Tracker, https://github.com/readyyeti/menu.py/issues
Platform: UNKNOWN
Classifier: Natural Language :: English
Classifier: Development Status :: 2 - Pre-Alpha
Classifier: Programming Language :: Python :: 3.10
Classifier: Programming Language :: Python :: 3.9
Classifier: Programming Language :: Python :: 3.8
Classifier: Programming Language :: Python :: 3.7
Classifier: Programming Language :: Python :: 3.6
Classifier: License :: OSI Approved :: MIT License
Classifier: Operating System :: Microsoft :: Windows
License-File: LICENSE
Requires-Dist: keyboard
